type_serialize/__init__.py
type_serialize/deserialize.py
type_serialize/errors.py
type_serialize/interface.py
type_serialize/numpy.py
type_serialize/protocols.py
type_serialize/serialize.py
type_serialize/to_boolean.py
type_serialize/inspect/__init__.py
type_serialize/inspect/bind.py
type_serialize/inspect/init_signature.py
type_serialize/inspect/member.py
type_serialize/inspect/types.py
type_serialize-2.1.0.dist-info/LICENSE
type_serialize-2.1.0.dist-info/METADATA
type_serialize-2.1.0.dist-info/WHEEL
type_serialize-2.1.0.dist-info/top_level.txt
type_serialize-2.1.0.dist-info/RECORD
